chronos/__init__.py
chronos/chronos.py
chronos_api-0.1.0.dist-info/LICENSE
chronos_api-0.1.0.dist-info/WHEEL
chronos_api-0.1.0.dist-info/METADATA
chronos_api-0.1.0.dist-info/RECORD
