Metadata-Version: 2.1
Name: chronos-api
Version: 0.1.0
Summary: API for my timesheet
Home-page: https://jonaylor89.github.io/chronos
License: MIT
Author: John Naylor
Author-email: jonaylor89@gmail.com
Requires-Python: >=3.6,<4.0
Classifier: Development Status :: 2 - Pre-Alpha
Classifier: Intended Audience :: Developers
Classifier: License :: OSI Approved :: MIT License
Classifier: Natural Language :: English
Classifier: Programming Language :: Python :: 3
Classifier: Programming Language :: Python :: 3.4
Classifier: Programming Language :: Python :: 3.5
Classifier: Programming Language :: Python :: 3.6
Classifier: Programming Language :: Python :: 3.7
Classifier: Programming Language :: Python :: 3.8
Requires-Dist: flask (>=1.1.1,<2.0.0)
Requires-Dist: google-api-python-client (>=1.7.11,<2.0.0)
Requires-Dist: google-auth-httplib2 (>=0.0.3,<0.0.4)
Requires-Dist: google-auth-oauthlib (>=0.4.1,<0.5.0)
Requires-Dist: gunicorn (>=20.0.4,<21.0.0)
Requires-Dist: iso8601 (>=0.1.12,<0.2.0)
Project-URL: Repository, https://github.com/jonaylor89/chronos
